im_futuretest_flask/__init__.py
im_futuretest_flask-0.1.3.dist-info/DESCRIPTION.rst
im_futuretest_flask-0.1.3.dist-info/METADATA
im_futuretest_flask-0.1.3.dist-info/RECORD
im_futuretest_flask-0.1.3.dist-info/WHEEL
im_futuretest_flask-0.1.3.dist-info/metadata.json
im_futuretest_flask-0.1.3.dist-info/top_level.txt
